{
  "version": "7",
  "dialect": "postgresql",
  "entries": [
    {
      "idx": 0,
      "version": "7",
      "when": 1730649600000,
      "tag": "0001_rewards_schema",
      "breakpoints": true
    },
    {
      "idx": 1,
      "version": "7",
      "when": 1730736000000,
      "tag": "0002_seed_quests",
      "breakpoints": true
    },
    {
      "idx": 2,
      "version": "7",
      "when": 1730822400000,
      "tag": "0003_seed_default_user",
      "breakpoints": true
    },
    {
      "idx": 3,
      "version": "7",
      "when": 1730908800000,
      "tag": "0004_quests_is_one_time_and_active_window",
      "breakpoints": true
    },
    {
      "idx": 4,
      "version": "7",
      "when": 1730995200000,
      "tag": "0005_transactions_client_category_hours",
      "breakpoints": true
    },
    {
      "idx": 5,
      "version": "7",
      "when": 1731081600000,
      "tag": "0006_strikes_removed",
      "breakpoints": true
    },
    {
      "idx": 6,
      "version": "7",
      "when": 1731196800000,
      "tag": "0007_levels_strike_limits_week_month",
      "breakpoints": true
    },
    {
      "idx": 7,
      "version": "7",
      "when": 1731283200000,
      "tag": "0008_system_settings_and_levels_bonus_multiplier",
      "breakpoints": true
    },
    {
      "idx": 9,
      "version": "7",
      "when": 1731456000000,
      "tag": "0010_user_groups",
      "breakpoints": true
    },
    {
      "idx": 10,
      "version": "7",
      "when": 1731542400000,
      "tag": "0011_users_balance_non_negative",
      "breakpoints": true
    }
  ]
}
